// class version 52.0 (52)
// access flags 0x21
public class Calculator {

  // compiled from: Calculator.java

  // access flags 0x1
  public <init>()V
   L0
    LINENUMBER 8 L0
    ALOAD 0
    INVOKESPECIAL java/lang/Object.<init> ()V
    RETURN
   L1
    LOCALVARIABLE this LCalculator; L0 L1 0
    MAXSTACK = 1
    MAXLOCALS = 1

  // access flags 0x1
  public add(II)I
   L0
    LINENUMBER 11 L0
    INVOKESTATIC java/lang/System.currentTimeMillis ()J
    LSTORE 3
   L1
    LINENUMBER 12 L1
    ILOAD 1
    ILOAD 2
    IADD
    ISTORE 5
   L2
    LINENUMBER 13 L2
    INVOKESTATIC java/lang/System.currentTimeMillis ()J
    LSTORE 6
   L3
    LINENUMBER 14 L3
    GETSTATIC java/lang/System.out : Ljava/io/PrintStream;
    LLOAD 6
    LLOAD 3
    LSUB
    INVOKEVIRTUAL java/io/PrintStream.println (J)V
   L4
    LINENUMBER 15 L4
    ILOAD 5
    IRETURN
   L5
    LOCALVARIABLE this LCalculator; L0 L5 0
    LOCALVARIABLE x I L0 L5 1
    LOCALVARIABLE y I L0 L5 2
    LOCALVARIABLE startTime J L1 L5 3
    LOCALVARIABLE result I L2 L5 5
    LOCALVARIABLE endTime J L3 L5 6
    MAXSTACK = 5
    MAXLOCALS = 8
}
