// class version 52.0 (52)
// access flags 0x21
public class Calculator {

  // compiled from: Calculator.java

  // access flags 0x1
  public <init>()V
   L0
    LINENUMBER 8 L0
    ALOAD 0
    INVOKESPECIAL java/lang/Object.<init> ()V
    RETURN
   L1
    LOCALVARIABLE this LCalculator; L0 L1 0
    MAXSTACK = 1
    MAXLOCALS = 1

  // access flags 0x1
  public add(II)I
   L0
    LINENUMBER 11 L0
    ILOAD 1
    ILOAD 2
    IADD
    ISTORE 3
   L1
    LINENUMBER 12 L1
    ILOAD 3
    IRETURN
   L2
    LOCALVARIABLE this LCalculator; L0 L2 0
    LOCALVARIABLE x I L0 L2 1
    LOCALVARIABLE y I L0 L2 2
    LOCALVARIABLE result I L1 L2 3
    MAXSTACK = 2
    MAXLOCALS = 4

  // access flags 0x1
  public sub(II)I
   L0
    LINENUMBER 16 L0
    ILOAD 1
    ILOAD 2
    ISUB
    ISTORE 3
   L1
    LINENUMBER 17 L1
    ILOAD 3
    IRETURN
   L2
    LOCALVARIABLE this LCalculator; L0 L2 0
    LOCALVARIABLE x I L0 L2 1
    LOCALVARIABLE y I L0 L2 2
    LOCALVARIABLE result I L1 L2 3
    MAXSTACK = 2
    MAXLOCALS = 4

  // access flags 0x1
  public mult(II)I
   L0
    LINENUMBER 22 L0
    ILOAD 1
    ILOAD 2
    IMUL
    ISTORE 3
   L1
    LINENUMBER 23 L1
    ILOAD 3
    IRETURN
   L2
    LOCALVARIABLE this LCalculator; L0 L2 0
    LOCALVARIABLE x I L0 L2 1
    LOCALVARIABLE y I L0 L2 2
    LOCALVARIABLE result I L1 L2 3
    MAXSTACK = 2
    MAXLOCALS = 4

  // access flags 0x1
  public div(II)I
   L0
    LINENUMBER 28 L0
    ILOAD 1
    ILOAD 2
    IDIV
    ISTORE 3
   L1
    LINENUMBER 29 L1
    ILOAD 3
    IRETURN
   L2
    LOCALVARIABLE this LCalculator; L0 L2 0
    LOCALVARIABLE x I L0 L2 1
    LOCALVARIABLE y I L0 L2 2
    LOCALVARIABLE result I L1 L2 3
    MAXSTACK = 2
    MAXLOCALS = 4

  // access flags 0x1
  public other()V
   L0
    LINENUMBER 35 L0
    ICONST_3
    ISTORE 1
   L1
    LINENUMBER 36 L1
    ICONST_5
    ISTORE 2
   L2
    LINENUMBER 38 L2
    ILOAD 1
    BIPUSH 10
    IF_ICMPGE L3
   L4
    LINENUMBER 39 L4
    GETSTATIC java/lang/System.out : Ljava/io/PrintStream;
    LDC "X is less than 10"
    INVOKEVIRTUAL java/io/PrintStream.println (Ljava/lang/String;)V
    GOTO L5
   L3
    LINENUMBER 41 L3
   FRAME APPEND [I I]
    GETSTATIC java/lang/System.out : Ljava/io/PrintStream;
    LDC "X is greater than 10"
    INVOKEVIRTUAL java/io/PrintStream.println (Ljava/lang/String;)V
   L5
    LINENUMBER 44 L5
   FRAME SAME
    ILOAD 1
    ICONST_3
    IF_ICMPNE L6
   L7
    LINENUMBER 45 L7
    BIPUSH 10
    ISTORE 1
    GOTO L8
   L6
    LINENUMBER 47 L6
   FRAME SAME
    BIPUSH 20
    ISTORE 1
   L8
    LINENUMBER 50 L8
   FRAME SAME
    ILOAD 2
    ILOAD 1
    IF_ICMPLE L9
   L10
    LINENUMBER 51 L10
    GETSTATIC java/lang/System.out : Ljava/io/PrintStream;
    LDC " y is greater than x"
    INVOKEVIRTUAL java/io/PrintStream.println (Ljava/lang/String;)V
    GOTO L11
   L9
    LINENUMBER 53 L9
   FRAME SAME
    GETSTATIC java/lang/System.out : Ljava/io/PrintStream;
    LDC " y is greater than y"
    INVOKEVIRTUAL java/io/PrintStream.println (Ljava/lang/String;)V
   L11
    LINENUMBER 55 L11
   FRAME SAME
    RETURN
   L12
    LOCALVARIABLE this LCalculator; L0 L12 0
    LOCALVARIABLE x I L1 L12 1
    LOCALVARIABLE y I L2 L12 2
    MAXSTACK = 2
    MAXLOCALS = 3

  // access flags 0x1
  public uncovered()V
   L0
    LINENUMBER 60 L0
    ICONST_0
    ISTORE 1
   L1
    LINENUMBER 62 L1
    ICONST_1
    ISTORE 2
   L2
   FRAME APPEND [I I]
    ILOAD 2
    BIPUSH 100
    IF_ICMPGE L3
   L4
    LINENUMBER 63 L4
    IINC 1 1
   L5
    LINENUMBER 62 L5
    IINC 2 1
    GOTO L2
   L3
    LINENUMBER 66 L3
   FRAME CHOP 1
    ILOAD 1
    IFLE L6
   L7
    LINENUMBER 67 L7
    IINC 1 -1
    GOTO L3
   L6
    LINENUMBER 70 L6
   FRAME SAME
    RETURN
   L8
    LOCALVARIABLE i I L2 L3 2
    LOCALVARIABLE this LCalculator; L0 L8 0
    LOCALVARIABLE x I L1 L8 1
    MAXSTACK = 2
    MAXLOCALS = 3

  // access flags 0x1
  public multiIfElse()V
   L0
    LINENUMBER 74 L0
    ICONST_3
    ISTORE 1
   L1
    LINENUMBER 76 L1
    ILOAD 1
    BIPUSH 10
    IF_ICMPGE L2
   L3
    LINENUMBER 77 L3
    GETSTATIC java/lang/System.out : Ljava/io/PrintStream;
    LDC "X is less than 10"
    INVOKEVIRTUAL java/io/PrintStream.println (Ljava/lang/String;)V
    GOTO L4
   L2
    LINENUMBER 78 L2
   FRAME APPEND [I]
    ILOAD 1
    BIPUSH 10
    IF_ICMPNE L5
   L6
    LINENUMBER 79 L6
    GETSTATIC java/lang/System.out : Ljava/io/PrintStream;
    LDC "X is equal than 10"
    INVOKEVIRTUAL java/io/PrintStream.println (Ljava/lang/String;)V
    GOTO L4
   L5
    LINENUMBER 81 L5
   FRAME SAME
    GETSTATIC java/lang/System.out : Ljava/io/PrintStream;
    LDC "X is greater than 10"
    INVOKEVIRTUAL java/io/PrintStream.println (Ljava/lang/String;)V
   L4
    LINENUMBER 84 L4
   FRAME SAME
    RETURN
   L7
    LOCALVARIABLE this LCalculator; L0 L7 0
    LOCALVARIABLE x I L1 L7 1
    MAXSTACK = 2
    MAXLOCALS = 2

  // access flags 0x1
  public deneme(I)V
   L0
    LINENUMBER 89 L0
    ILOAD 1
    IFEQ L1
   L2
    LINENUMBER 90 L2
    IINC 1 1
   L1
    LINENUMBER 93 L1
   FRAME SAME
    RETURN
   L3
    LOCALVARIABLE this LCalculator; L0 L3 0
    LOCALVARIABLE x I L0 L3 1
    MAXSTACK = 1
    MAXLOCALS = 2
}
